nitsa/__init__.py
nitsa/cli.py
nitsa-0.0.0a0.dist-info/LICENSE
nitsa-0.0.0a0.dist-info/METADATA
nitsa-0.0.0a0.dist-info/WHEEL
nitsa-0.0.0a0.dist-info/entry_points.txt
nitsa-0.0.0a0.dist-info/top_level.txt
nitsa-0.0.0a0.dist-info/RECORD
