Metadata-Version: 2.1
Name: nitsa
Version: 0.0.0a0
Summary: Placeholder
Home-page: https://github.com/Florents-Tselai/nitsa
Author: Florents Tselai
License: MIT License
Project-URL: Issues, https://github.com/Florents-Tselai/nitsa/issues
Project-URL: CI, https://github.com/Florents-Tselai/nitsa/actions
Project-URL: Changelog, https://github.com/Florents-Tselai/nitsa/releases
Requires-Python: >=3.7
License-File: LICENSE
Requires-Dist: click
Requires-Dist: setuptools
Requires-Dist: pip
Provides-Extra: test
Requires-Dist: pytest ; extra == 'test'
Requires-Dist: pytest-cov ; extra == 'test'
Requires-Dist: black ; extra == 'test'
Requires-Dist: ruff ; extra == 'test'
Requires-Dist: click ; extra == 'test'
